fabular/__init__.py
fabular/__main__.py
fabular/client.py
fabular/comm.py
fabular/config.py
fabular/crypt.py
fabular/server.py
fabular/utils.py
fabular-0.0.dev2.dist-info/LICENSE
fabular-0.0.dev2.dist-info/METADATA
fabular-0.0.dev2.dist-info/WHEEL
fabular-0.0.dev2.dist-info/entry_points.txt
fabular-0.0.dev2.dist-info/top_level.txt
fabular-0.0.dev2.dist-info/RECORD
