Metadata-Version: 2.1
Name: fabular
Version: 0.0.dev2
Summary: A command-line chat app for secure communication between you and your friends!
Home-page: https://github.com/phdenzel/fabular
Author: Philipp Denzel
Author-email: phdenzel@gmail.com
License: GNU General Public License v3.0
Keywords: command line,chat,secure,encryption,server,client
Platform: UNKNOWN
Classifier: Development Status :: 3 - Alpha
Classifier: License :: OSI Approved :: GNU General Public License v3 (GPLv3)
Classifier: Operating System :: POSIX
Classifier: Environment :: Console
Classifier: Programming Language :: Python
Classifier: Programming Language :: Python :: 3
Classifier: Programming Language :: Python :: 3.6
Classifier: Programming Language :: Python :: 3.7
Classifier: Programming Language :: Python :: 3.8
Classifier: Programming Language :: Python :: 3.9
Classifier: Topic :: Communications
Classifier: Topic :: Communications :: Chat
Classifier: Topic :: Security
Requires-Python: >=3.6
Requires-Dist: cryptography
Requires-Dist: pyngrok
